pyxlsbwriter/__init__.py
pyxlsbwriter/writer.py
pyxlsbwriter/xlsx_writer.py
pyxlsbwriter-0.0.4.dist-info/METADATA
pyxlsbwriter-0.0.4.dist-info/WHEEL
pyxlsbwriter-0.0.4.dist-info/top_level.txt
pyxlsbwriter-0.0.4.dist-info/RECORD
