Metadata-Version: 2.4
Name: pyxlsbwriter
Version: 0.0.4
Summary: A Python library to write XLSB and XLSX files.
Author: Krzysztof Duśko
Classifier: Programming Language :: Python :: 3
Classifier: License :: OSI Approved :: MIT License
Classifier: Operating System :: OS Independent
Requires-Python: >=3.8
Provides-Extra: test
Requires-Dist: pyodbc; extra == "test"
Provides-Extra: examples
Requires-Dist: memory-profiler; extra == "examples"
